easy_athena/__init__.py
tests/__init__.py
tests/test_default.py
easy_athena-0.0.9.dist-info/LICENSE
easy_athena-0.0.9.dist-info/METADATA
easy_athena-0.0.9.dist-info/WHEEL
easy_athena-0.0.9.dist-info/top_level.txt
easy_athena-0.0.9.dist-info/RECORD
