Metadata-Version: 2.1
Name: easy-athena
Version: 0.0.9
Summary: This package helps you use AWS Athena easily.
Home-page: https://github.com/jaden-git/easy_athena
Author: JunYeong Park
Author-email: dahuin000@gmail.com
License: MIT
Download-URL: https://github.com/da-huin/jaden-git/archive/master.zip
Platform: UNKNOWN
Classifier: Programming Language :: Python :: 3
Requires-Dist: boto3
